[[
  {
    "id": 1,
    "name": "Suzette Cain",
    "username": "user1",
    "email": "user1@gmail.com",
    "password": "md5(pass)",
    "img": "https://via.placeholder.com/400/929/fff/?text=user1",
    "date_create": "2021-10-26 01:23:49"
  },
  {
    "id": 2,
    "name": "Mcpherson Hughes",
    "username": "user2",
    "email": "user2@gmail.com",
    "password": "md5(pass)",
    "img": "https://via.placeholder.com/400/780/fff/?text=user2",
    "date_create": "2021-02-27 11:20:10"
  },
  {
    "id": 3,
    "name": "Amelia Gates",
    "username": "user3",
    "email": "user3@gmail.com",
    "password": "md5(pass)",
    "img": "https://via.placeholder.com/400/774/fff/?text=user3",
    "date_create": "2021-05-08 08:17:03"
  },
  {
    "id": 4,
    "name": "Debora Elliott",
    "username": "user4",
    "email": "user4@gmail.com",
    "password": "md5(pass)",
    "img": "https://via.placeholder.com/400/991/fff/?text=user4",
    "date_create": "2020-03-22 12:48:04"
  },
  {
    "id": 5,
    "name": "Potter Battle",
    "username": "user5",
    "email": "user5@gmail.com",
    "password": "md5(pass)",
    "img": "https://via.placeholder.com/400/809/fff/?text=user5",
    "date_create": "2020-05-05 06:01:55"
  },
  {
    "id": 6,
    "name": "Leonor Alexander",
    "username": "user6",
    "email": "user6@gmail.com",
    "password": "md5(pass)",
    "img": "https://via.placeholder.com/400/902/fff/?text=user6",
    "date_create": "2021-03-04 11:04:20"
  },
  {
    "id": 7,
    "name": "Morris Carroll",
    "username": "user7",
    "email": "user7@gmail.com",
    "password": "md5(pass)",
    "img": "https://via.placeholder.com/400/719/fff/?text=user7",
    "date_create": "2020-05-31 10:58:50"
  },
  {
    "id": 8,
    "name": "Alexandria Herring",
    "username": "user8",
    "email": "user8@gmail.com",
    "password": "md5(pass)",
    "img": "https://via.placeholder.com/400/868/fff/?text=user8",
    "date_create": "2021-02-23 10:42:38"
  },
  {
    "id": 9,
    "name": "Richards Cameron",
    "username": "user9",
    "email": "user9@gmail.com",
    "password": "md5(pass)",
    "img": "https://via.placeholder.com/400/835/fff/?text=user9",
    "date_create": "2021-07-01 12:25:10"
  },
  {
    "id": 10,
    "name": "Alana Head",
    "username": "user10",
    "email": "user10@gmail.com",
    "password": "md5(pass)",
    "img": "https://via.placeholder.com/400/805/fff/?text=user10",
    "date_create": "2020-07-16 07:25:31"
  }
]